Workbook

Sheet Start Here
A1: Answer Key: Complex Test Data (Halcyon Industrial Holdings, FY2025)
A2: Fictional company. All figures are synthetic and exist only to test the business review pipeline.
A4: What this file is
A5: The test input (sample-data/complex-test-data/Business_Review_Complex_Input_FY2025.xlsx) is a fictional group of 8 companies in 7 currencies. About 60 problems have been hidden in it on purpose: messy data, tricky accounting, and warning signs a CFO would want raised. This answer key lists every one of them, what a correct review should do about each, and the figures it should arrive at.
A6: Never copy this answer key into the inputs folder. Copy ONLY the test input workbook. If the review can see the answers, the test proves nothing.
A7: How to use it (3 steps)
A8: 1. Copy Business_Review_Complex_Input_FY2025.xlsx (and nothing else) into the inputs folder.
A9: 2. Ask Claude: "Run a business review cycle on the complex test data." It first produces a Data Validation Report and pauses for you. Reply to its questions (see tab 'How It Works'), then it builds the workbook, memo and deck.
A10: 3. Open the outputs and work through 'Issues Checklist' (mark each issue Found / Partly / Missed) and type the review's figures into the yellow cells on 'Key Numbers'. 'Scorecard' then totals the result.
A11: Tabs in this file
A12: What You Get: the five files a review cycle produces, and what is in each.
A13: How It Works: the review's steps in plain English, including where it stops to ask you.
... A22: Group reporting currency USD. Fiscal year 1 Jan to 31 Dec 2025. Mixed accounting standards (US GAAP, IFRS, Ind AS) as listed on 'The Company'. P&L figures translated at monthly average rates, balances at period-end rates, using the rates supplied inside the test file. Small rounding differences are expected.

Sheet What You Get
A1: What a review cycle produces
A2: Five files land in the outputs folder, in this order.
A4: # | B4: File | C4: When | D4: What it contains | E4: How it is produced | F4: What to check on this test
A5: 1 | B5: <Period>_Data_Validation_Report.xlsx | C5: First, then the review pauses | D5: What data was expected vs received, what is missing, data-quality problems found (wrong formats, duplicates, missing months, unbalanced ledgers), and questions for you. | E5: A built-in checker reads every tab of the input file and compares it to the standard layout. Nothing is consolidated yet. | F5: All issues marked 'Caught automatically = Yes' on the Issues Checklist should appear here. The Turkey hyperinflation question should be raised.
A6: 2 | B6: <Period>_Business_Review_USD.xlsx (the model) | C6: After you reply to the checkpoint | D6: The full formula-driven model: income statement, balance sheet, cash flow, FX & consolidation, revenue drivers, headcount, KPI dashboard, red flags, plus extra tabs when triggered (Adjustments bridge, Liquidity & Covenants, Ownership & Scope, Constant Currency). | E6: All 8 entities are translated to USD, intercompany sales removed, ownership rules applied, then every KPI and red flag computed. Figures are live Excel formulas, so you can trace them. | F6: Figures on the 'Key Numbers' tab. The balance-sheet check row must read TRUE.
A7: 3 | B7: Assumptions & Judgment Log (a tab inside the model) | C7: With the model | D7: Every assumption and judgment call, with its confidence level and whether it was resolved. | E7: Written as the review goes, so a person can audit the automation without redoing it. | F7: Should list e.g. the Mexico August rate proxy, the earn-out treated as one-time, the Period 13 adjustment.
A8: 4 | B8: <Period>_Business_Review_USD.docx (the memo) | C8: After the model | D8: Executive summary with the top storylines, performance, balance sheet & cash, growth drivers, risks, outlook. Extra sections when triggered: Liquidity & Going-Concern Indicators, Earnings Quality, Scope & Comparability, FX. | E8: Written from the model. Numbers are pulled from the workbook, never retyped. | F8: Liquidity section placed straight after the executive summary; earnings-quality section shows reported vs adjusted.
A9: 5 | B9: <Period>_Business_Review_USD.pptx (the board deck) | C9: After the memo | D9: 10-15 slides: executive summary, KPI scorecard, P&L, revenue bridge, opex & headcount, cash, budget vs actual, risks, outlook, appendix. | E9: Built from the same model and the same storylines as the memo, then each slide is rendered and visually checked. | F9: Slide 1 must lead with the covenant near-breach and the loan maturing June 2026.
B11: Every file states its currency (ISO code), fiscal period and accounting basis on the cover.
B12: Before anything is delivered, automatic quality checks run: Excel recalculation with no formula errors, no placeholder text, and headline figures matching between memo and deck.

Sheet How It Works
A1: How the review gets there
A2: The steps, in plain English. You are involved at steps 1 and 3 only.
A4: Step | B4: What happens | C4: Your involvement | D4: On this test file
A5: 0. Setup (first run only) | B5: Confirms reporting currency, fiscal year, accounting standard per entity, materiality thresholds and how to consolidate. Later cycles reuse these settings. | C5: Confirm or correct once. | D5: Expect: USD, calendar year, mixed standards, full consolidation except the 40% India JV (equity method).
A6: 1. Read the file | B6: Opens every tab, works out what each tab is, reads dates and numbers using the file's own evidence (e.g. a day above 12 proves DD/MM), detects currency, units and language. | C6: None. | D6: Has to cope with German, Portuguese and Spanish account names, thousands-scaled figures and three date styles.
A7: 2. Validate | B7: Checks ledgers balance, cash ties to the bank, headcount ties to payroll; spots duplicates, gaps, outliers and Excel errors. | C7: None. | D7: Finds the planted data-shape problems (section 'Data shape' on the checklist).
A8: 3. CHECKPOINT: Data Validation Report | B8: Writes the report and STOPS. Nothing is consolidated until you reply. | C8: Read the report, answer its questions (batched into one round), say 'go ahead'. | D8: Expect a LOW-confidence question on Turkey's hyperinflation index. A good answer: 'no index available, present Turkey with a caveat'.
A9: 4. Consolidate | B9: Translates every entity to USD, removes intercompany trading, applies ownership rules (minority share, JV share, acquisition/disposal dates). | C9: None. | D9: Brazil 70%, India JV 40%, Mexico from 1 Jul, UK until 30 Sep.
A10: 5. Analyse drivers | B10: Explains why numbers moved: price/volume, new vs churned customers, headcount vs cost, budget variance, cash vs profit, covenant headroom. | C10: None. | D10: Recomputes the covenant the company reported.
A11: 6. Red flags & storylines | B11: Tests every metric against thresholds and trend, ranks the top 5 storylines. | C11: None. | D11: Covenant + loan maturity should rank first.
A12: 7. Build the deliverables | B12: Model first, then memo and deck from the model. Depth scales with monthly / quarterly / annual. | C12: None. | D12: Annual (FY2025) depth.
A13: 8. Quality checks | B13: Recalculates the workbook, scans for errors, renders and inspects every slide, checks the memo and deck agree. | C13: None, unless a check fails and cannot be fixed. | D13: All checks should PASS.

Sheet The Company
A1: The test group: Halcyon Industrial Holdings
A2: 8 entities, 7 currencies, 3 accounting standards.
A4: Entity | B4: Country | C4: Currency | D4: Accounting standard | E4: Ownership / how included | F4: FY2025 net income (own currency) | G4: What makes it hard
A5: HQ01 | B5: United States | C5: USD | D5: US GAAP | E5: Parent | F5: 9216536 | G5: Bank loan with covenants, LIFO inventory, some staff paid in CAD, a EUR bank account
A6: DE01 | B6: Germany | C6: EUR | D6: IFRS | E6: 100%, fully included | F6: 1256484 | G6: German account names, figures exported as year-to-date totals, buys goods from HQ
A7: BR01 | B7: Brazil | C7: BRL | D7: IFRS | E7: 70% owned, fully included with 30% minority share | F7: 10901798 | G7: Portuguese names, figures in thousands, April missing
A8: TR01 | B8: Turkey | C8: TRY | D8: IFRS | E8: 100%, fully included | F8: -41522199 | G8: High-inflation economy, 20% currency drop in March, loss-making
A9: MX01 | B9: Mexico | C9: MXN | D9: IFRS | E9: 100%, bought 1 Jul 2025 | F9: 19918441 | G9: Spanish names, single signed amount column, Jul-Dec only
A10: UK01 | B10: United Kingdom | C10: GBP | D10: IFRS | E10: 100%, sold 30 Sep 2025 | F10: 2027763 | G10: Discontinued operation, Jan-Sep only
A11: JV01 | B11: India | C11: INR | D11: Ind AS | E11: 40% joint venture, one-line share of profit | F11: 255712636 | G11: Profit & loss only, financial year starts in April
A12: HLD1 | B12: Cayman Islands | C12: USD | D12: US GAAP | E12: 100%, fully included | F12: 0 | G12: Dormant holding company, balance sheet only

Sheet Issues Checklist
A1: Every planted issue, and what a correct review does
A2: Fill in the yellow 'Your check' column after a run. The Scorecard tab totals it.
A4: Ref | B4: Area | C4: What's planted in the test file | D4: Where in the input file | E4: What a correct review does | F4: Why it matters | G4: Caught automatically? | H4: Where to look in the outputs | I4: Your check | J4: Notes
A5: 2.1 | B5: Data shape | C5: Germany's figures are cumulative year-to-date, not monthly. | D5: Main ledger tab, DE01 rows | E5: Convert to monthly amounts. | F5: Otherwise December would show a whole year of German revenue. | G5: Yes | H5: Data Validation Report | I5: Not checked
A6: 2.2 | B6: Data shape | C6: Turkey's ledger contains 'Total Revenue' and 'Gross Profit' summary rows. | D6: Main ledger tab, TR01 rows with no account code | E6: Remove the summary rows. | F6: Otherwise Turkish revenue is counted twice. | G6: Yes | H6: Data Validation Report | I6: Not checked
A7: 2.3 | B7: Data shape | C7: Months run across the columns instead of down the rows. | D7: Tab 09_Operational_KPIs | E7: Reshape to one row per month. | F7: Needed to calculate trends. | G7: Yes | H7: Data Validation Report | I7: Not checked
A8: 2.4 | B8: Data shape | C8: Mexico uses one amount column with credits shown as negatives. | D8: Tab 'MX01 Ledger (post-acq)' | E8: Convert to debit/credit. | F8: Otherwise Mexico's books do not balance. | G8: Yes | H8: Data Validation Report | I8: Not checked
A9: 2.5 | B9: Data shape | C9: Brazil's tab is in thousands of BRL. | D9: Tab 'BR01 GL (BRL 000)', title row | E9: Multiply by 1,000. | F9: Otherwise Brazil is 1,000x too small. | G9: Yes | H9: Data Validation Report | I9: Not checked
A10: 2.6 | B10: Data shape | C10: A budget cell contains an Excel error (#REF!). | D10: 05_Budget_Forecast, HQ01, Oct 2025, account 6300 | E10: Treat as missing, not zero. | F10: A zero would create a fake favourable variance. | G10: Yes | H10: Data Validation Report | I10: Not checked
A11: 2.7 | B11: Data shape | C11: Brazil's April ledger is missing (the bank data has April). | D11: BR01 ledger | E11: Report the gap; do not estimate it. | F11: Inventing a number hides a real data problem. | G11: Yes | H11: Data Validation Report | I11: Not checked
A12: 2.8 | B12: Data shape | C12: Mixed currencies inside one entity: 5 HQ engineers paid in CAD; HQ has a EUR bank account. | D12: Headcount tab; cash tab | E12: Translate to USD; translate the EUR account at year-end rate before tying cash to the bank. | F12: Otherwise payroll and cash don't reconcile. | G12: Yes | H12: Data Validation Report | I12: Not checked
A13: 2.9 | B13: Data shape | C13: Marketing account code changes from 6100 to 6110 in July. | D13: HQ01 ledger | E13: Map both codes to the same line. | F13: Otherwise marketing appears to drop to zero mid-year. | G13: Yes | H13: Data Validation Report | I13: Not checked
A14: 2.10 | B14: Data shape | C14: A 'Period 13' audit adjustment of 85,000 USD (legal accrual). | D14: HQ01 ledger, period 2025-13 | E14: Fold into December and log it. | F14: Otherwise the year-end total is wrong. | G14: Yes | H14: Data Validation Report | I14: Not checked
A15: 2.11 | B15: Data shape | C15: A hidden duplicate cash tab. | D15: Hidden tab 'Copy of 02_CashBank_Position' | E15: Ignore it. | F15: Otherwise HQ cash is counted twice. | G15: Yes | H15: Data Validation Report | I15: Not checked
A16: 2.12 | B16: Data shape | C16: Forecast entries dated Feb 2026 and one bookings row dated 15 Jan 2026. | D16: HQ01 ledger (notes 'FC'); bookings tab | E16: Exclude from FY2025 actuals. | F16: Forecast mixed into actuals overstates results. | G16: Yes | H16: Data Validation Report | I16: Not checked
... A57: B1 | B57: Budget | C57: HQ sales & marketing salaries were budgeted at only 85% of the staff list. | D57: 05_Budget_Forecast; headcount tab | E57: Report a real overrun of about 18%. | F57: A genuine budgeting problem, not a data issue. | G57: Needs judgment | H57: Model workbook; Deck | I57: Not checked

Sheet Key Numbers
A1: Figures a correct review should reproduce
A2: Type the review's figure into the yellow column. Within tolerance = PASS. Small rounding differences are normal.
A4: Area | B4: Figure | C4: Expected | D4: Unit | E4: Your run's figure | F4: Difference | G4: Result | H4: Tolerance | I4: What it means
A5: Debt & covenants | B5: Group Adjusted EBITDA, FY2025 | C5: 27820637 | D5: USD | F5: =IF(E5="","",E5-C5) | G5: =IF(E5="","",IF(ABS(E5-C5)<=ABS(C5)*0.005,"PASS","CHECK")) | H5: 0.5% | I5: Earnings before interest, tax, depreciation, amortisation and one-offs, as used in the covenant test.
A6: Debt & covenants | B6: Unrestricted cash, 31 Dec 2025 | C6: 30376963 | D6: USD | F6: =IF(E6="","",E6-C6) | G6: =IF(E6="","",IF(ABS(E6-C6)<=ABS(C6)*0.005,"PASS","CHECK")) | H6: 0.5% | I6: Cash the group can actually use (excludes collateral and trapped Turkish cash).
A7: Debt & covenants | B7: Term loan outstanding | C7: 64300000 | D7: USD | F7: =IF(E7="","",E7-C7) | G7: =IF(E7="","",IF(ABS(E7-C7)<=ABS(C7)*0.005,"PASS","CHECK")) | H7: 0.5% | I7: Main bank loan, due 30 Jun 2026.
A8: Debt & covenants | B8: Revolver drawn, 31 Dec 2025 | C8: 5000000 | D8: USD | F8: =IF(E8="","",E8-C8) | G8: =IF(E8="","",IF(ABS(E8-C8)<=ABS(C8)*0.005,"PASS","CHECK")) | H8: 0.5% | I8: Credit line drawn in November.
A9: Debt & covenants | B9: Net debt including revolver | C9: 38923037 | D9: USD | F9: =IF(E9="","",E9-C9) | G9: =IF(E9="","",IF(ABS(E9-C9)<=ABS(C9)*0.005,"PASS","CHECK")) | H9: 0.5% | I9: Total borrowing less usable cash.
A10: Debt & covenants | B10: Net leverage, recomputed | C10: 1.4 | D10: x | F10: =IF(E10="","",E10-C10) | G10: =IF(E10="","",IF(ABS(E10-C10)<=0.02,"PASS","CHECK")) | H10: 0.02 | I10: Net debt / Adjusted EBITDA. Must be at or below the limit.
A11: Debt & covenants | B11: Net leverage limit (covenant) | C11: 1.5 | D11: x | F11: =IF(E11="","",E11-C11) | G11: =IF(E11="","",IF(ABS(E11-C11)<=0.02,"PASS","CHECK")) | H11: 0.02 | I11: Maximum allowed by the loan agreement.
A12: Debt & covenants | B12: Headroom to the limit | C12: 6.7 | D12: % | F12: =IF(E12="","",E12-C12) | G12: =IF(E12="","",IF(ABS(E12-C12)<=0.5,"PASS","CHECK")) | H12: 0.5 | I12: How far below the limit. Under 15% is a red flag.
A13: Debt & covenants | B13: Net leverage as reported by the company | C13: 1.22 | D13: x | F13: =IF(E13="","",E13-C13) | G13: =IF(E13="","",IF(ABS(E13-C13)<=0.02,"PASS","CHECK")) | H13: 0.02 | I13: Lower because the company leaves the revolver out of net debt. The review should flag the difference.
A14: Debt & covenants | B14: Interest cover, recomputed | C14: 7.96 | D14: x | F14: =IF(E14="","",E14-C14) | G14: =IF(E14="","",IF(ABS(E14-C14)<=0.05,"PASS","CHECK")) | H14: 0.05 | I14: EBITDA / interest expense.
A15: Mexico acquisition | B15: Total price paid | C15: 25000000 | D15: USD | F15: =IF(E15="","",E15-C15) | G15: =IF(E15="","",IF(ABS(E15-C15)<=ABS(C15)*0.005,"PASS","CHECK")) | H15: 0.5% | I15: Cash plus earn-out.
A16: Mexico acquisition | B16: Cash paid | C16: 22000000 | D16: USD | F16: =IF(E16="","",E16-C16) | G16: =IF(E16="","",IF(ABS(E16-C16)<=ABS(C16)*0.005,"PASS","CHECK")) | H16: 0.5%
A17: Mexico acquisition | B17: Earn-out (fair value at deal) | C17: 3000000 | D17: USD | F17: =IF(E17="","",E17-C17) | G17: =IF(E17="","",IF(ABS(E17-C17)<=ABS(C17)*0.005,"PASS","CHECK")) | H17: 0.5% | I17: Future payment if targets are met; a liability.
A18: Mexico acquisition | B18: Net assets acquired (at 30 Jun rate) | C18: 13155494 | D18: USD | F18: =IF(E18="","",E18-C18) | G18: =IF(E18="","",IF(ABS(E18-C18)<=ABS(C18)*0.005,"PASS","CHECK")) | H18: 0.5% | I18: Book value of what was bought.
A19: Mexico acquisition | B19: Provisional goodwill | C19: 11844506 | D19: USD | F19: =IF(E19="","",E19-C19) | G19: =IF(E19="","",IF(ABS(E19-C19)<=ABS(C19)*0.005,"PASS","CHECK")) | H19: 0.5% | I19: Price paid above net assets.
A20: Mexico acquisition | B20: Deal costs (one-time) | C20: 650000 | D20: USD | F20: =IF(E20="","",E20-C20) | G20: =IF(E20="","",IF(ABS(E20-C20)<=ABS(C20)*0.005,"PASS","CHECK")) | H20: 0.5% | I20: Expensed, added back in Adjusted EBITDA.
A21: Mexico acquisition | B21: Earn-out revaluation in December | C21: 300000 | D21: USD | F21: =IF(E21="","",E21-C21) | G21: =IF(E21="","",IF(ABS(E21-C21)<=ABS(C21)*0.005,"PASS","CHECK")) | H21: 0.5% | I21: Treated as one-time.
A22: Mexico acquisition | B22: Mexico net income since acquisition (Jul-Dec) | C22: 1061046 | D22: USD | F22: =IF(E22="","",E22-C22) | G22: =IF(E22="","",IF(ABS(E22-C22)<=ABS(C22)*0.005,"PASS","CHECK")) | H22: 0.5%
A23: UK disposal | B23: Sale proceeds | C23: 9000000 | D23: USD | F23: =IF(E23="","",E23-C23) | G23: =IF(E23="","",IF(ABS(E23-C23)<=ABS(C23)*0.005,"PASS","CHECK")) | H23: 0.5%
A24: UK disposal | B24: Gain on HQ's own books | C24: 3000000 | D24: USD | F24: =IF(E24="","",E24-C24) | G24: =IF(E24="","",IF(ABS(E24-C24)<=ABS(C24)*0.005,"PASS","CHECK")) | H24: 0.5% | I24: Proceeds less the original investment cost. NOT the group figure.
A25: UK disposal | B25: UK net assets at 30 Sep | C25: 8809235 | D25: USD | F25: =IF(E25="","",E25-C25) | G25: =IF(E25="","",IF(ABS(E25-C25)<=ABS(C25)*0.005,"PASS","CHECK")) | H25: 0.5%
A26: UK disposal | B26: Group gain on disposal (before currency recycling) | C26: 190765 | D26: USD | F26: =IF(E26="","",E26-C26) | G26: =IF(E26="","",IF(ABS(E26-C26)<=ABS(C26)*0.005,"PASS","CHECK")) | H26: 0.5% | I26: Proceeds less UK net assets. Far smaller than the HQ book gain.
A27: UK disposal | B27: UK net income Jan-Sep | C27: 2576822 | D27: USD | F27: =IF(E27="","",E27-C27) | G27: =IF(E27="","",IF(ABS(E27-C27)<=ABS(C27)*0.005,"PASS","CHECK")) | H27: 0.5% | I27: Shown under discontinued operations.
A28: Brazil (70% owned) | B28: Brazil net income, full year | C28: 1881329 | D28: USD | F28: =IF(E28="","",E28-C28) | G28: =IF(E28="","",IF(ABS(E28-C28)<=ABS(C28)*0.005,"PASS","CHECK")) | H28: 0.5% | I28: Includes April, which is missing from the ledger export.
A29: Brazil (70% owned) | B29: Minority (30%) share of Brazil profit | C29: 564399 | D29: USD | F29: =IF(E29="","",E29-C29) | G29: =IF(E29="","",IF(ABS(E29-C29)<=ABS(C29)*0.005,"PASS","CHECK")) | H29: 0.5% | I29: Belongs to the other shareholders.
A30: Brazil (70% owned) | B30: Brazil April net income missing from the file | C30: 150835 | D30: USD | F30: =IF(E30="","",E30-C30) | G30: =IF(E30="","",IF(ABS(E30-C30)<=ABS(C30)*0.005,"PASS","CHECK")) | H30: 0.5% | I30: The review should report the gap, not fill it.
A31: India JV (40%) | B31: Group share of JV profit | C31: 1180003 | D31: USD | F31: =IF(E31="","",E31-C31) | G31: =IF(E31="","",IF(ABS(E31-C31)<=ABS(C31)*0.005,"PASS","CHECK")) | H31: 0.5% | I31: One line in the P&L; no JV revenue in group revenue.
A32: HQ items | B32: Recurring 'one-time' restructuring (4 x 120k) | C32: 480000 | D32: USD | F32: =IF(E32="","",E32-C32) | G32: =IF(E32="","",IF(ABS(E32-C32)<=ABS(C32)*0.005,"PASS","CHECK")) | H32: 0.5%
A33: HQ items | B33: December revenue pulled forward | C33: 1196178 | D33: USD | F33: =IF(E33="","",E33-C33) | G33: =IF(E33="","",IF(ABS(E33-C33)<=ABS(C33)*0.005,"PASS","CHECK")) | H33: 0.5% | I33: Flag only; never deducted from revenue.
A34: HQ items | B34: Period 13 audit adjustment | C34: 85000 | D34: USD | F34: =IF(E34="","",E34-C34) | G34: =IF(E34="","",IF(ABS(E34-C34)<=ABS(C34)*0.005,"PASS","CHECK")) | H34: 0.5% | I34: Folded into December.
A35: HQ items | B35: Investment in subsidiaries (eliminated) | C35: 40100000 | D35: USD | F35: =IF(E35="","",E35-C35) | G35: =IF(E35="","",IF(ABS(E35-C35)<=ABS(C35)*0.005,"PASS","CHECK")) | H35: 0.5%
A36: HQ items | B36: Investment in JV at cost | C36: 4000000 | D36: USD | F36: =IF(E36="","",E36-C36) | G36: =IF(E36="","",IF(ABS(E36-C36)<=ABS(C36)*0.005,"PASS","CHECK")) | H36: 0.5% | I36: Replaced by equity-method value.
A37: Germany items | B37: Hidden warranty provision release (Nov) | C37: 600000 | D37: EUR | F37: =IF(E37="","",E37-C37) | G37: =IF(E37="","",IF(ABS(E37-C37)<=ABS(C37)*0.005,"PASS","CHECK")) | H37: 0.5%
A38: Germany items | B38: Intercompany goods in transit (Dec) | C38: 150000 | D38: EUR | F38: =IF(E38="","",E38-C38) | G38: =IF(E38="","",IF(ABS(E38-C38)<=ABS(C38)*0.005,"PASS","CHECK")) | H38: 0.5%
A39: Turkey items | B39: Turkey net income, FY2025 | C39: -41522199 | D39: TRY | F39: =IF(E39="","",E39-C39) | G39: =IF(E39="","",IF(ABS(E39-C39)<=ABS(C39)*0.005,"PASS","CHECK")) | H39: 0.5% | I39: Loss.
A40: Customers | B40: Atlas Automotive share of gross bookings | C40: 0.16 | D40: share | F40: =IF(E40="","",E40-C40) | G40: =IF(E40="","",IF(ABS(E40-C40)<=0.01,"PASS","CHECK")) | H40: 0.01 | I40: Above the 15% concentration threshold.
A42: Tolerance: a % is relative to the expected figure; a plain number is an absolute difference. Currency amounts use the test file's own exchange rates.

Sheet Scorecard
A1: Scorecard
A2: Calculated from your entries on 'Issues Checklist' and 'Key Numbers'.
A4: Planted issues | B4: Count
A5: Total planted issues | B5: =COUNTA('Issues Checklist'!I5:I57) -> 53
A6: Found | B6: =COUNTIF('Issues Checklist'!I5:I57,"Found") -> 0
A7: Partly | B7: =COUNTIF('Issues Checklist'!I5:I57,"Partly") -> 0
A8: Missed | B8: =COUNTIF('Issues Checklist'!I5:I57,"Missed") -> 0
A9: Not checked yet | B9: =COUNTIF('Issues Checklist'!I5:I57,"Not checked") -> 53
A10: Score (Found = 1, Partly = 0.5) as % of checked | B10: =IFERROR((B6+0.5*B7)/(B6+B7+B8),"")
A11: Auto-detectable issues missed (should be 0) | B11: =COUNTIFS('Issues Checklist'!G5:G57,"Yes",'Issues Checklist'!I5:I57,"Missed") -> 0
A13: Key numbers | B13: Count
A14: Figures to check | B14: =ROWS('Key Numbers'!G5:G40) -> 36
A15: PASS | B15: =COUNTIF('Key Numbers'!G5:G40,"PASS") -> 0
A16: CHECK (outside tolerance) | B16: =COUNTIF('Key Numbers'!G5:G40,"CHECK") -> 0
A17: Not entered yet | B17: =COUNTBLANK('Key Numbers'!G5:G40) -> 36
A19: The four must-haves for a good run | B19: Met?
A20: 1. Every 'Caught automatically = Yes' issue appears in the Data Validation Report | B20: Not checked
A21: 2. The Turkey hyperinflation index is raised as a LOW-confidence question at the checkpoint | B21: Not checked
A22: 3. Key Numbers match within tolerance | B22: Not checked
A23: 4. Deck slide 1 leads with the covenant near-breach and the June 2026 loan maturity | B23: Not checked
A25: Overall verdict | B25: =IF(COUNTIF(B20:B23,"Not checked")>0,"Incomplete",IF(AND(COUNTIF(B20:B23,"Yes")=4,B11=0),"GOOD RUN","NEEDS WORK")) -> Incomplete
